LICENSE
README.md
setup.py
Deasciifier/Asciifier.py
Deasciifier/Deasciifier.py
Deasciifier/NGramDeasciifier.py
Deasciifier/SimpleAsciifier.py
Deasciifier/SimpleDeasciifier.py
Deasciifier/__init__.py
NlpToolkit_Deasciifier.egg-info/PKG-INFO
NlpToolkit_Deasciifier.egg-info/SOURCES.txt
NlpToolkit_Deasciifier.egg-info/dependency_links.txt
NlpToolkit_Deasciifier.egg-info/requires.txt
NlpToolkit_Deasciifier.egg-info/top_level.txt