Metadata-Version: 2.1
Name: NlpToolkit-Deasciifier
Version: 1.0.15
Summary: Turkish Asciifier/Deasciifier Library
Home-page: https://github.com/StarlangSoftware/TurkishDeasciifier-Py
Author: olcaytaner
Author-email: olcay.yildiz@ozyegin.edu.tr
License: UNKNOWN
Platform: UNKNOWN
License-File: LICENSE
